fbxtools
