Metadata-Version: 1.1
Name: fbxtools
Version: 1.1
Summary: Provide intialisation, connect and disconnect functions for Freebox OS application.
Home-page: http://github.com/herrersystem/fbxtools
Author: herrersystem
Author-email: contact@evhunter.fr
License: GNU General Public License (GPL)
Keywords: fbx freebox
Platform: UNKNOWN
Classifier: Development Status :: 4 - Beta
Classifier: License :: OSI Approved :: GNU General Public License (GPL)
Classifier: Programming Language :: Python :: 3
Classifier: Programming Language :: Python :: 3.4
